fuzzable/__init__.py
fuzzable/__main__.py
fuzzable/analysis/__init__.py
fuzzable/analysis/angr.py
fuzzable/analysis/ast.py
fuzzable/analysis/binja.py
fuzzable/cli.py
fuzzable/config.py
fuzzable/generate.py
fuzzable/log.py
fuzzable/metrics.py
fuzzable-2.0.6.dist-info/entry_points.txt
fuzzable-2.0.6.dist-info/LICENSE.md
fuzzable-2.0.6.dist-info/WHEEL
fuzzable-2.0.6.dist-info/METADATA
fuzzable-2.0.6.dist-info/RECORD
