Metadata-Version: 2.1
Name: fuzzable
Version: 2.0.6
Summary: Framework for Automating Fuzzable Target Discovery with Static Analysis
Home-page: https://codemuch.tech/fuzzable
License: MIT
Keywords: security,fuzzing,vulnerability-research,binary-analysis
Author: ex0dus
Author-email: ex0dus@codemuch.tech
Requires-Python: >=3.8,<4.0
Classifier: License :: OSI Approved :: MIT License
Classifier: Programming Language :: Python :: 3
Classifier: Programming Language :: Python :: 3.10
Classifier: Programming Language :: Python :: 3.8
Classifier: Programming Language :: Python :: 3.9
Requires-Dist: angr (>=9.2.8,<10.0.0)
Requires-Dist: lief (>=0.12.1,<0.13.0)
Requires-Dist: scikit-criteria (>=0.7,<0.8)
Requires-Dist: tree-sitter (>=0.20.0,<0.21.0)
Requires-Dist: typer[all] (>=0.6.1,<0.7.0)
Project-URL: Documentation, https://github.com/ex0dus-0x/fuzzable/wiki
Project-URL: Repository, https://github.com/ex0dus-0x/fuzzable
